cag/MANIFETS.in
cag/__init__.py
cag/cli.py
cag/cookiecutter.json
cag/framework/__init__.py
cag/framework/component.py
cag/framework/analyzer/Readme.md
cag/framework/analyzer/__init__.py
cag/framework/analyzer/analyzer_base.py
cag/framework/analyzer/aql_queries.py
cag/framework/analyzer/operator_enum.py
cag/framework/analyzer/query_builder.py
cag/framework/analyzer/objects/Edge.py
cag/framework/analyzer/objects/GraphFlow.py
cag/framework/analyzer/objects/Node.py
cag/framework/analyzer/objects/__init__.py
cag/framework/annotator/__init__.py
cag/framework/annotator/annotator_base.py
cag/framework/annotator/registered_pipes.py
cag/framework/annotator/element/__init__.py
cag/framework/annotator/element/graph_elements.py
cag/framework/annotator/element/orchestrator.py
cag/framework/annotator/instance/__init__.py
cag/framework/annotator/instance/dummy.py
cag/framework/annotator/instance/emotion_orchestrator.py
cag/framework/annotator/instance/empath_orchestrator.py
cag/framework/annotator/instance/hedge_orchestrator.py
cag/framework/annotator/instance/iptcmedia_topic_orchestrator.py
cag/framework/annotator/instance/keyterms_orchestrator.py
cag/framework/annotator/instance/mpqa_orchestrator.py
cag/framework/annotator/instance/ner_orchestrator.py
cag/framework/annotator/instance/openalex_concept_orchestrator.py
cag/framework/annotator/instance/toxicity_orchestrator.py
cag/framework/annotator/pipe/__init__.py
cag/framework/annotator/pipe/linguistic/__init__.py
cag/framework/annotator/pipe/linguistic/discourse_marker.py
cag/framework/annotator/pipe/linguistic/emotion.py
cag/framework/annotator/pipe/linguistic/empath.py
cag/framework/annotator/pipe/linguistic/hedge.py
cag/framework/annotator/pipe/linguistic/iptcmedia_topic.py
cag/framework/annotator/pipe/linguistic/keyterms.py
cag/framework/annotator/pipe/linguistic/metadata.py
cag/framework/annotator/pipe/linguistic/mpqa.py
cag/framework/annotator/pipe/linguistic/oaconcept.py
cag-1.6.0.dist-info/entry_points.txt
cag-1.6.0.dist-info/LICENSE
cag-1.6.0.dist-info/WHEEL
cag-1.6.0.dist-info/METADATA
cag-1.6.0.dist-info/RECORD
