Metadata-Version: 2.1
Name: cag
Version: 1.6.0
Summary: This is a general framework to create arango db graphs and annotate them.
Keywords: graph,architectural framework,graph creator,graph annotator
Author-email: Roxanne El Baff <roxanne.elbaff@dlr.de>, Tobias Hecking <tobias.hecking@dlr.de>
Requires-Python: >=3.8
Classifier: License :: OSI Approved :: MIT License
Classifier: Programming Language :: Python
Classifier: Programming Language :: Python :: 3
Classifier: Development Status :: 3 - Alpha
Classifier: Intended Audience :: Science/Research
Requires-Dist: dataclasses>=0.6
Requires-Dist: spacy>=3.4.1
Requires-Dist: spacy_arguing_lexicon>=0.0.3
Requires-Dist: empath>=0.89
Requires-Dist: pytest>=7.1.2
Requires-Dist: networkx>=2.8.5
Requires-Dist: nltk>=3.4.5
Requires-Dist: pyvis>=0.2.1
Requires-Dist: tqdm>=4.43.0
Requires-Dist: python-arango>=7.4.1
Requires-Dist: pyArango>=2.0.1
Requires-Dist: tomli>=2.0.1
Requires-Dist: transformers>=4.26.1
Requires-Dist: tenacity>=8.2.2
Requires-Dist: pandas
Requires-Dist: python-slugify~=6.1.2
Requires-Dist: rich~=12.6.0
Requires-Dist: cookiecutter>=2.1.1
Requires-Dist: python-dotenv>=1.0.0
Requires-Dist: pip-tools ; extra == "dev"
Requires-Dist: pytest ; extra == "dev"
Project-URL: Homepage, https://github.com/DLR-SC/corpus-annotation-graph-builder
Provides-Extra: dev
